{
  "$schema": "file:///C:/Users/bluef/OneDrive/Desktop/BlueEarthCat%20Minecraft%20Launcher/Nebula/build-choya/schemas/ServerMetaSchema.schema.json",
  "meta": {
    "version": "1.0.0",
    "name": "Choya Server (Minecraft 1.20.6)",
    "description": "Choya Server Running Minecraft 1.20.6 (Fabric v0.17.3)",
    "icon": "How to set the server icon: https://github.com/dscalzi/Nebula#setting-the-server-icon",
    "address": "minecb.mcv.kr",
    "discord": {
      "shortId": "<FILL IN OR REMOVE DISCORD OBJECT>",
      "largeImageText": "<FILL IN OR REMOVE DISCORD OBJECT>",
      "largeImageKey": "<FILL IN OR REMOVE DISCORD OBJECT>"
    },
    "mainServer": true,
    "autoconnect": true
  },
  "fabric": {
    "version": "0.17.3"
  },
  "untrackedFiles": []
}